odoo/addons/oca_psc_team/README.rst
odoo/addons/oca_psc_team/__init__.py
odoo/addons/oca_psc_team/__manifest__.py
odoo/addons/oca_psc_team/demo/github_repository.xml
odoo/addons/oca_psc_team/demo/project.xml
odoo/addons/oca_psc_team/demo/psc_category.xml
odoo/addons/oca_psc_team/models/__init__.py
odoo/addons/oca_psc_team/models/github_repository.py
odoo/addons/oca_psc_team/models/project.py
odoo/addons/oca_psc_team/models/psc_category.py
odoo/addons/oca_psc_team/readme/CONTRIBUTORS.rst
odoo/addons/oca_psc_team/readme/DESCRIPTION.rst
odoo/addons/oca_psc_team/readme/USAGE.rst
odoo/addons/oca_psc_team/security/ir.model.access.csv
odoo/addons/oca_psc_team/static/description/icon.png
odoo/addons/oca_psc_team/static/description/index.html
odoo/addons/oca_psc_team/static/src/img/project_apps_store.png
odoo/addons/oca_psc_team/static/src/img/project_construction.png
odoo/addons/oca_psc_team/static/src/img/project_services.png
odoo/addons/oca_psc_team/static/src/img/project_tools_administration.png
odoo/addons/oca_psc_team/static/src/img/project_vertical_medical.png
odoo/addons/oca_psc_team/tests/__init__.py
odoo/addons/oca_psc_team/tests/test_project.py
odoo/addons/oca_psc_team/tests/test_psc_category.py
odoo/addons/oca_psc_team/views/project_views.xml
odoo/addons/oca_psc_team/views/psc_category_views.xml
odoo14_addon_oca_psc_team-14.0.1.0.0.dist-info/METADATA
odoo14_addon_oca_psc_team-14.0.1.0.0.dist-info/WHEEL
odoo14_addon_oca_psc_team-14.0.1.0.0.dist-info/top_level.txt
odoo14_addon_oca_psc_team-14.0.1.0.0.dist-info/RECORD
