Metadata-Version: 2.1
Name: odoo14-addon-oca-psc-team
Version: 14.0.1.0.0
Summary: This module allows you to store PSC details in project.These details will be displayed in PSC Teams in website.
Home-page: https://github.com/OCA/oca-custom
Author: Odoo Community Association (OCA), Surekha Technologies
Author-email: support@odoo-community.org
License: AGPL-3
Platform: UNKNOWN
Classifier: Programming Language :: Python
Classifier: Framework :: Odoo
Classifier: License :: OSI Approved :: GNU Affero General Public License v3
Requires-Python: >=3.6
Requires-Dist: odoo14-addon-github-connector
Requires-Dist: odoo14-addon-project-members
Requires-Dist: odoo (<14.1dev,>=14.0a)
